risk_adjustment_model/__init__.py
risk_adjustment_model/beneficiary.py
risk_adjustment_model/category.py
risk_adjustment_model/commercial_model.py
risk_adjustment_model/mapper.py
risk_adjustment_model/medicare_model.py
risk_adjustment_model/model.py
risk_adjustment_model/reference_data/commercial/v07/2023/category_definition.json
risk_adjustment_model/reference_data/commercial/v07/2023/diag_to_category_map.txt
risk_adjustment_model/reference_data/commercial/v07/2023/group_definition.json
risk_adjustment_model/reference_data/commercial/v07/2023/hierarchy_definition.json
risk_adjustment_model/reference_data/commercial/v07/2023/ndc_to_category_map.txt
risk_adjustment_model/reference_data/commercial/v07/2023/proc_to_category_map.txt
risk_adjustment_model/reference_data/commercial/v07/2023/weights.csv
risk_adjustment_model/reference_data/commercial/v07/2024/category_definition.json
risk_adjustment_model/reference_data/commercial/v07/2024/diag_to_category_map.txt
risk_adjustment_model/reference_data/commercial/v07/2024/group_definition.json
risk_adjustment_model/reference_data/commercial/v07/2024/hierarchy_definition.json
risk_adjustment_model/reference_data/commercial/v07/2024/ndc_to_category_map.txt
risk_adjustment_model/reference_data/commercial/v07/2024/proc_to_category_map.txt
risk_adjustment_model/reference_data/commercial/v07/2024/weights.csv
risk_adjustment_model/reference_data/commercial/v08/2025/category_definition.json
risk_adjustment_model/reference_data/commercial/v08/2025/diag_to_category_map.txt
risk_adjustment_model/reference_data/commercial/v08/2025/group_definition.json
risk_adjustment_model/reference_data/commercial/v08/2025/hierarchy_definition.json
risk_adjustment_model/reference_data/commercial/v08/2025/ndc_to_category_map.txt
risk_adjustment_model/reference_data/commercial/v08/2025/proc_to_category_map.txt
risk_adjustment_model/reference_data/commercial/v08/2025/weights.csv
risk_adjustment_model-0.5.1.dist-info/LICENSE
risk_adjustment_model-0.5.1.dist-info/METADATA
risk_adjustment_model-0.5.1.dist-info/WHEEL
risk_adjustment_model-0.5.1.dist-info/RECORD
