Metadata-Version: 2.1
Name: risk_adjustment_model
Version: 0.5.1
Summary: Python implementation of healthcare risk adjustment models
Author: Phil Fehlinger
Author-email: pjfehlinger@gmail.com
Requires-Python: >=3.12,<4.0
Classifier: Programming Language :: Python :: 3
Classifier: Programming Language :: Python :: 3.12
Classifier: Programming Language :: Python :: 3.13
